maads-tml/__init__.py
maads-tml/sendfiles.py
maadstml/__init__.py
maadstml/readpdf.py
maadstml/sendfiles.py
maadstml/tmltextsummary.py
maadstmlmedia/__init__.py
maadstmlmedia/readpdf.py
maadstmlmedia/sendfiles.py
maadstmlmedia/tmltextsummary.py
maadstmlmedia-1.2.dist-info/METADATA
maadstmlmedia-1.2.dist-info/WHEEL
maadstmlmedia-1.2.dist-info/license.txt
maadstmlmedia-1.2.dist-info/top_level.txt
maadstmlmedia-1.2.dist-info/RECORD
