Metadata-Version: 2.1
Name: maadstmlmedia
Version: 1.2
Summary: Multi-Agent Accelerator for Data Science (MAADS): Transactional Machine Learning
Home-page: https://github.com/smaurice101/transactionalmachinelearning
Author: Sebastian Maurice
Author-email: sebastian.maurice@otics.ca
License: MIT License
Keywords: multi-agent, transactional machine learning, audio, video, images, data streams, data science, optimization, prescriptive analytics, machine learning, automl,auto-ml,artificial intelligence,predictive analytics,advanced analytics
License-File: license.txt
Requires-Dist: easyocr
Requires-Dist: speech-recognition
Requires-Dist: moviepy
